cloud_foundry/__init__.py
cloud_foundry/archive_builder.py
cloud_foundry/cloud_foundry.py
cloud_foundry/mail_publisher.py
cloud_foundry/python_archive_builder.py
cloud_foundry/pulumi/__init__.py
cloud_foundry/pulumi/api_waf.py
cloud_foundry/pulumi/cdn.py
cloud_foundry/pulumi/cdn_api_origin.py
cloud_foundry/pulumi/cdn_site_origin.py
cloud_foundry/pulumi/cloudfront_waf.py
cloud_foundry/pulumi/connection_store.py
cloud_foundry/pulumi/content_repository.py
cloud_foundry/pulumi/custom_domain.py
cloud_foundry/pulumi/document_repository.py
cloud_foundry/pulumi/domain.py
cloud_foundry/pulumi/function.py
cloud_foundry/pulumi/log_group.py
cloud_foundry/pulumi/publisher.py
cloud_foundry/pulumi/python_function.py
cloud_foundry/pulumi/queue.py
cloud_foundry/pulumi/rest_api.py
cloud_foundry/pulumi/rest_api_logging_role.py
cloud_foundry/pulumi/site_bucket.py
cloud_foundry/pulumi/topic.py
cloud_foundry/pulumi/ui_publisher.py
cloud_foundry/pulumi/websocket_api.py
cloud_foundry/pulumi/websocket_function.py
cloud_foundry/services/mail_publisher.py
cloud_foundry/services/authorization_api/security_lambda.py
cloud_foundry/utils/aws_openapi_editor.py
cloud_foundry/utils/hash_comparator.py
cloud_foundry/utils/logger.py
cloud_foundry/utils/names.py
cloud_foundry/utils/openapi_editor.py
cloud_foundry/utils/websocket_utils.py
cloud_foundry-0.1.3.dist-info/METADATA
cloud_foundry-0.1.3.dist-info/WHEEL
cloud_foundry-0.1.3.dist-info/licenses/LICENSE
cloud_foundry-0.1.3.dist-info/RECORD
