Metadata-Version: 2.4
Name: cloud-foundry
Version: 0.1.3
Summary: cloud-foundry is a curated set of cloud components that can be used to assemble cloud-based applications.
Project-URL: Documentation, https://github.com/DanRepik/cloud-foundry
Project-URL: Source, https://github.com/DanRepik/cloud-foundry
Author-email: Daniel Repik <danrepik@icloud.com>
License: Apache-2.0
License-File: LICENSE
Classifier: Operating System :: OS Independent
Classifier: Programming Language :: Python :: 3.9
Requires-Python: >=3.9
Requires-Dist: boto3
Requires-Dist: pulumi
Requires-Dist: pulumi-aws
Provides-Extra: dev
Requires-Dist: black>=23.0.0; extra == 'dev'
Requires-Dist: flit>=3.9; extra == 'dev'
Requires-Dist: isort>=5.12.0; extra == 'dev'
Requires-Dist: mypy>=1.0.0; extra == 'dev'
Requires-Dist: pytest-cov>=4.0.0; extra == 'dev'
Requires-Dist: pytest>=7.0; extra == 'dev'
